py_pkg_chijane/__init__.py
py_pkg_chijane/hello.py
py_pkg_chijane-0.0.1.dist-info/LICENSE
py_pkg_chijane-0.0.1.dist-info/METADATA
py_pkg_chijane-0.0.1.dist-info/WHEEL
py_pkg_chijane-0.0.1.dist-info/top_level.txt
py_pkg_chijane-0.0.1.dist-info/RECORD
