Metadata-Version: 2.1
Name: py-pkg-chijane
Version: 0.0.1
Summary: A small example package
Home-page: https://github.com/ChenCookie/py_pkg_chijane
Author: CJC
Author-email: cookie877128@gmail.com
Classifier: Programming Language :: Python :: 3
Classifier: License :: OSI Approved :: MIT License
Classifier: Operating System :: OS Independent
Requires-Python: >=3.6
License-File: LICENSE
